{"assets/.DS_Store":["assets/.DS_Store"],"assets/fonts/ANTQUABI.TTF":["assets/fonts/ANTQUABI.TTF"],"assets/fonts/ANTQUAI.TTF":["assets/fonts/ANTQUAI.TTF"],"assets/fonts/amsterdam.ttf":["assets/fonts/amsterdam.ttf"],"assets/fonts/cambria.ttc":["assets/fonts/cambria.ttc"],"assets/fonts/cambriab.ttf":["assets/fonts/cambriab.ttf"],"assets/fonts/cambriai.ttf":["assets/fonts/cambriai.ttf"],"assets/fonts/cambriaz.ttf":["assets/fonts/cambriaz.ttf"],"assets/fonts/leguespartan.ttf":["assets/fonts/leguespartan.ttf"],"assets/fonts/quicksand.ttf":["assets/fonts/quicksand.ttf"],"assets/fonts/richard.otf":["assets/fonts/richard.otf"],"assets/icons/bell.png":["assets/icons/bell.png"],"assets/icons/booking.png":["assets/icons/booking.png"],"assets/icons/check.png":["assets/icons/check.png"],"assets/icons/deals.png":["assets/icons/deals.png"],"assets/icons/gallery.png":["assets/icons/gallery.png"],"assets/icons/home.png":["assets/icons/home.png"],"assets/icons/hotel.png":["assets/icons/hotel.png"],"assets/icons/imagedummy.png":["assets/icons/imagedummy.png"],"assets/icons/logo.jpeg":["assets/icons/logo.jpeg"],"assets/icons/logo2.jpeg":["assets/icons/logo2.jpeg"],"assets/icons/logs.png":["assets/icons/logs.png"],"assets/icons/pending.png":["assets/icons/pending.png"],"assets/icons/products.png":["assets/icons/products.png"],"assets/icons/profile.png":["assets/icons/profile.png"],"assets/icons/reports.png":["assets/icons/reports.png"],"assets/icons/saved.png":["assets/icons/saved.png"],"assets/icons/services.png":["assets/icons/services.png"],"assets/icons/stylists.png":["assets/icons/stylists.png"],"assets/icons/tower.png":["assets/icons/tower.png"],"assets/icons/tower_icon.png":["assets/icons/tower_icon.png"],"assets/icons/vote.png":["assets/icons/vote.png"],"packages/cupertino_icons/assets/CupertinoIcons.ttf":["packages/cupertino_icons/assets/CupertinoIcons.ttf"]}